CHANGES.rst
LICENSE.txt
MANIFEST.in
README.rst
requirements.txt
setup.py
src/napoleon2html/__init__.py
src/napoleon2html.egg-info/PKG-INFO
src/napoleon2html.egg-info/SOURCES.txt
src/napoleon2html.egg-info/dependency_links.txt
src/napoleon2html.egg-info/requires.txt
src/napoleon2html.egg-info/top_level.txt
src/napoleon2html.egg-info/zip-safe