Metadata-Version: 1.1
Name: napoleon2html
Version: 0.2.0
Summary: Wrappers to translate Napoleon/Sphinx docstrings to HTML.
Home-page: https://github.com/Bystroushaak/napoleon2html
Author: Bystroushaak
Author-email: bystrousak@kitakitsune.org
License: MIT
Platform: UNKNOWN
Classifier: Intended Audience :: Developers
Classifier: Programming Language :: Python :: 2
Classifier: Programming Language :: Python :: 2.7
Classifier: License :: OSI Approved :: MIT License
